dataLib/__init__.py
dataLib/core.py
dataLibFarah/__init__.py
dataLibFarah/core.py
test/__init__.py
test/test_datalib.py
dataLibFarah-0.0.1.dist-info/METADATA
dataLibFarah-0.0.1.dist-info/WHEEL
dataLibFarah-0.0.1.dist-info/top_level.txt
dataLibFarah-0.0.1.dist-info/RECORD
