Metadata-Version: 2.1
Name: dataLibFarah
Version: 0.0.1
Summary: A library for data manipulation, analysis, and visualization.
Home-page: https://github.com/riahiFarah/DataLib.git
Author: Farah Riahi
Author-email: farah.riahi2@gmail.com
Classifier: Programming Language :: Python :: 3
Classifier: License :: OSI Approved :: MIT License
Classifier: Operating System :: OS Independent
Requires-Python: >=3.7
Requires-Dist: pandas (>=1.0)
Requires-Dist: numpy (>=1.19)
Requires-Dist: matplotlib (>=3.0)
Requires-Dist: scikit-learn (>=0.24)
Requires-Dist: scipy (>=1.5)
Provides-Extra: dev
Requires-Dist: pytest (>=6.0) ; extra == 'dev'
Requires-Dist: pytest-cov ; extra == 'dev'
Requires-Dist: twine (>=4.0.2) ; extra == 'dev'
